{
  "year": 2010,
  "references": [{
    "title": " 'endl er a nd U. Radok",
    "authors": ["llison", "G. l"],
    "venue": "GeofJl!)'''. Res.,",
    "year": 1993
  }, {
    "title": "Snowfa ll in high sout he rn la ti tudes",
    "authors": ["H. Bromw ich. D."],
    "venue": "ReI'. Geo/,/o's.. 26 (1), 149 168",
    "year": 1988
  }, {
    "title": "IT\\· iew o f ic t\" rheology for ice shec t m odellin g. Cold R~~",
    "authors": ["J Budd. \\\\ '. F. a nd T. H"],
    "venue": "Sri. Teehl/ol.,",
    "year": 1989
  }, {
    "title": "Isotopes, cl im atc a nd ice shcet d ynamics",
    "authors": ["Budd"],
    "venue": "F a nd \\ : I. 1\\ lo rga n ",
    "year": 1977
  }, {
    "title": "Finite elemelll ana lysis or twodimensio na l longirudinal sec tio n now on Law Dome. A",
    "authors": ["R.J. Budd. \\\\ '. F a nd"],
    "venue": "r. Rowden-Rich",
    "year": 1985
  }, {
    "title": "A now model and a time scale 101' the ice co re from Camp CClllury",
    "authors": ["Dansgaard", "\\I", "S.J.Johnscn"],
    "venue": "Green land. J Claciol",
    "year": 1969
  }, {
    "title": "Volcanic aerosol and ozone depletion with in the Anta rctic polar \\'onex during the austral spring",
    "authors": ["T. Deshler", "A. Adriani. G.P. Gobbi", "D.J. H ofm\"nn", "B.J.G. di Donfra ncesco"],
    "venue": "J o hnson",
    "year": 1992
  }, {
    "title": "\\ l id-H olocene ice sheet recession li'om th e \\\\ 'ilkes Land cOlllinel1la[ shelr",
    "authors": ["E. Domac k"],
    "venue": "Linick",
    "year": 1991
  }, {
    "title": "Holocene deglaciation. sca-b'C I change and the emergence ort he \\\\' indmill lslands, Budd Coast, .\\nt a rn ica",
    "authors": ["Goodwin", "1. D"],
    "venue": "Q]lal. Res",
    "year": 1993
  }, {
    "title": "On the Al1la rctic cOlllribut ion to Ho locene sea-Ie\\T I",
    "authors": ["Goodwin", "1. D"],
    "year": 1995
  }, {
    "title": "andT. \\\\'illi amson",
    "authors": ["A.J. Gow"],
    "year": 1976
  }, {
    "title": "Acidity of po lar ice cores in relation to absolute dat",
    "authors": ["U. Hammer. C"],
    "venue": "RE Res",
    "year": 1980
  }, {
    "title": "Th e stead y-state crysra l size or deronning ice",
    "authors": ["T.H. a nd L. Jun."],
    "venue": "\"11111. Glaciol .. 20. 13 18. J ouzcl. J anrl6olhel:l . 1987. \\ 'osrok ice co re: a cont inuous isotope temperature record ove r the last climatic cycle 160,000 years . .",
    "year": 1994
  }, {
    "title": "Discontinuous Oow, ice texture, and din cont ent in the basa l layers o f the Devon Island ice ca p",
    "authors": ["R Koerner"],
    "venue": "J Claeiol. ,",
    "year": 1979
  }, {
    "title": "C lima tic impact or the mid-firteenth cemury Kuwae ca ldera format ion, as reconstructed rrom hi storical and proxy data",
    "authors": ["K.D. Pang"],
    "venue": "r",
    "year": 1993
  }, {
    "title": "Laboratory stud ies or Oow properties a nd a ssocia ted structures in Ho locene and I \\'isconsin ice. (1\\1.Sc",
    "authors": ["Va n", "IVci Li"],
    "year": 1994
  }, {
    "title": "lee formation and ice struct ure on Law Dome, Antarc ti ca",
    "authors": ["Z. Xie"],
    "venue": "AIIII. (;/aciol., 6, 150- 153.",
    "year": 1985
  }, {
    "title": "Phys ical cha racteristics or the snow and ice cover",
    "authors": ["Xie. Z", "J. Li", ":--I. IV. Young"],
    "year": 1989
  }, {
    "title": "Lorius a nd P",
    "authors": ["Yao", "T. n", "J. R . Pe tit", "C. .J. J ouzel"],
    "venue": "DU\\·a l",
    "year": 1990
  }, {
    "title": "llId 8 olh.ers",
    "authors": ["A. Zielinski. G"],
    "venue": "system. Science,",
    "year": 1994
  }],
  "id": "SP:113165ce3d357306f3a51a4f47d9b0ca3b537849",
  "authors": [{
    "name": "VAN OMME",
    "affiliations": []
  }, {
    "name": "W. SKINNER",
    "affiliations": []
  }, {
    "name": "M. F. FITZPATRICK",
    "affiliations": []
  }],
  "abstractText": "The a im of deep ice drilling on L aw Dome, Anta rc ti ca, has been to exploit the special cha racteri stics o f L aw Dome summ it , i. e. Iow tem p e raLUre and hig h acc umul a ti o n near a n ice di v id e, to obta in a hi g h-reso luti o n ice co re for clim a ti c / e lwironmenta l studi es of the H o locene a nd the L ast Glacial M a xi mum (LGM ). Dri 11 ing was comple ted in February 1993, when basal ice conta ining sma ll fragments of rock was reached a t a depth of 11 96 m. Acc urate ice dating, obtained by counting a nnua l layers revea led by fine-deta il bIHO, peroxide a nd electrical-conducti\\ ·it y measurements, is continuous down to 399 m, co rres po nding to a da te o f I\\D 1304. Sulpha te concentrati o n Ill easu rements, m ade a rou nd dept hs where cond ucti v i t y trac i ng i nd ica tes \\'olcanic fa llo ut , a ll ow confirm atio n of the dating (for Ag ung in 1963 a nd Tambo ra in (815) or estim a tes of the erupti o n d a te from the ice da ting (for the Kuwae, Va nuatu, erupti on ~1+57) . The lower part of the co re is dated by extra polating the layer-counting usi ng a si mple model o f the ice [low. At the LG~I, ice-fabric measurements show a la rge dec rease (250 to 1+ Illm 2 ) in crys tal size a nd a na rrow m ax imum in (-ax is verti ca lity. The m a in zone of strong sing lepole fabrics however, is loca ted higher up in a broad zone around 900 m. Oxygen-i so to pe (15 180 ) meas urements show H olocene ice down to 111 3 m, the LGNI a t 11 33 m a nd warm ( bl~O about the same as H olocene) ice near the base of the ice shee t. The LGM/H olocene 0180 shift o f 7.0%0, onl y ~ I %0 la rger than for Vosto k, indicates tha t Law Dome rem a ined a n independent ice cap and was not ove rridden by th e inland ice sheet in the Glac ia l."
}